vipermoon.py
vipermoon-0.5.0.dist-info/METADATA
vipermoon-0.5.0.dist-info/WHEEL
vipermoon-0.5.0.dist-info/entry_points.txt
vipermoon-0.5.0.dist-info/RECORD
