Metadata-Version: 2.4
Name: vipermoon
Version: 0.5.0
Summary: A Lua interpreter implemented in Python
License: MIT
Author: George Munyoro
Author-email: george.munyoro@icloud.com
Requires-Python: >=3.13
Classifier: License :: OSI Approved :: MIT License
Classifier: Programming Language :: Python :: 3
Classifier: Programming Language :: Python :: 3.13
Classifier: Programming Language :: Python :: 3.14
Requires-Dist: click (>=8.3.0,<9.0.0)
Requires-Dist: colorama (>=0.4.6,<0.5.0)
